ociogen/__init__.py
ociogen/core.py
ociogen/gui.py
ociogen/ociogen.py
ociogen/data/__init__.py
ociogen/data/colorspaces.yaml
ociogen/data/config.json
ociogen/data/config.yaml
ociogen/utilities/__init__.py
ociogen/utilities/colorimetry.py
ociogen/utilities/transfer_functions.py
ociogen-0.2.4.dist-info/METADATA
ociogen-0.2.4.dist-info/WHEEL
ociogen-0.2.4.dist-info/entry_points.txt
ociogen-0.2.4.dist-info/licenses/LICENSE.md
ociogen-0.2.4.dist-info/RECORD
