Metadata-Version: 2.4
Name: ociogen
Version: 0.2.4
Summary: OCIOGen simplifies OpenColorIO config creation with a user-friendly GUI, flexible YAML definitions, automatic LUT discovery, and command-line generation capabilities.
Author-email: Jed Smith <jed.coma316@passmail.net>
License-File: LICENSE.md
Requires-Python: >=3.7
Requires-Dist: opencolorio>=2.0
Requires-Dist: pyyaml>=3.11
